diel_models/__init__.py
diel_models/biomass_adjuster.py
diel_models/day_night_creator.py
diel_models/diel_models_creator.py
diel_models/nitrate_uptake_ratio.py
diel_models/photon_reaction_inhibitor.py
diel_models/pipeline.py
diel_models/storage_pool_generator.py
DielModels-1.1.0.dist-info/LICENSE
DielModels-1.1.0.dist-info/METADATA
DielModels-1.1.0.dist-info/WHEEL
DielModels-1.1.0.dist-info/top_level.txt
DielModels-1.1.0.dist-info/RECORD
